[
    {
        "title":"Immi- en emigratie; leeftijd (31 dec.), burgerlijke staat, geboorteland",
        "start":"2025-11-07",
        "country":"Netherlands",
        "source":"CBS API",
        "topic":"Demography",
        "url":"https:\/\/opendata.cbs.nl\/statline"
    },
    {
        "title":"Werknemers op 31 december; immigranten EU\/EFTA, afgeleid migratiedoel",
        "start":"2025-10-31",
        "country":"Netherlands",
        "source":"CBS API",
        "topic":"Demography",
        "url":"https:\/\/opendata.cbs.nl\/statline"
    },
    {
        "title":"Werknemers op 31 december, immigranten niet-EU\/EFTA, migratiemotief",
        "start":"2025-10-31",
        "country":"Netherlands",
        "source":"CBS API",
        "topic":"Demography",
        "url":"https:\/\/opendata.cbs.nl\/statline"
    },
    {
        "title":"Immigratie en emigratie; geslacht, leeftijd, geboorteland, regio",
        "start":"2025-07-18",
        "country":"Netherlands",
        "source":"CBS API",
        "topic":"Demography",
        "url":"https:\/\/opendata.cbs.nl\/statline"
    },
    {
        "title":"Immi- en emigratie; geslacht, leeftijd, nationaliteit, regio",
        "start":"2025-07-17",
        "country":"Netherlands",
        "source":"CBS API",
        "topic":"Demography",
        "url":"https:\/\/opendata.cbs.nl\/statline"
    },
    {
        "title":"Vaccination against influenza of population aged 65 and over",
        "start":"2025-07-15",
        "country":"EU",
        "source":"Eurostat API",
        "topic":"Population",
        "url":"https:\/\/ec.europa.eu\/eurostat\/data\/database"
    },
    {
        "title":"Healthy life years by sex (from 2004 onwards)",
        "start":"2025-07-04",
        "country":"EU",
        "source":"Eurostat API",
        "topic":"Population",
        "url":"https:\/\/ec.europa.eu\/eurostat\/data\/database"
    },
    {
        "title":"Live births (total) by metropolitan region",
        "start":"2024-05-08",
        "country":"EU",
        "source":"Eurostat API",
        "topic":"Population",
        "url":"https:\/\/ec.europa.eu\/eurostat\/data\/database"
    },
    {
        "title":"Levend geboren kind; migratieachtergrond en leeftijd moeder; 1996-2022",
        "start":"2023-09-22",
        "country":"Netherlands",
        "source":"CBS API",
        "topic":"Demography",
        "url":"https:\/\/opendata.cbs.nl\/statline"
    },
    {
        "title":"Geboorte; vruchtbaarheid, migratieachtergrond en generatie moeder;2010-2022",
        "start":"2023-08-07",
        "country":"Netherlands",
        "source":"CBS API",
        "topic":"Demography",
        "url":"https:\/\/opendata.cbs.nl\/statline"
    },
    {
        "title":"Self-reported unmet needs for health care by sex, age, specific reasons and degree of urbanisation",
        "start":"2022-11-25",
        "country":"EU",
        "source":"Eurostat API",
        "topic":"Population",
        "url":"https:\/\/ec.europa.eu\/eurostat\/data\/database"
    },
    {
        "title":"Self-reported unmet needs for health care by specific reasons, level of disability (activity limitation), sex and age",
        "start":"2022-11-25",
        "country":"EU",
        "source":"Eurostat API",
        "topic":"Population",
        "url":"https:\/\/ec.europa.eu\/eurostat\/data\/database"
    },
    {
        "title":"Overall perceived social support by sex, age and country of birth",
        "start":"2022-11-08",
        "country":"EU",
        "source":"Eurostat API",
        "topic":"Population",
        "url":"https:\/\/ec.europa.eu\/eurostat\/data\/database"
    },
    {
        "title":"Smoking of tobacco products by sex, age and country of birth",
        "start":"2022-11-08",
        "country":"EU",
        "source":"Eurostat API",
        "topic":"Population",
        "url":"https:\/\/ec.europa.eu\/eurostat\/data\/database"
    },
    {
        "title":"Self-reported unmet needs for specific health care-related services due to financial reasons by sex, age and degree of urbanisation",
        "start":"2022-10-28",
        "country":"EU",
        "source":"Eurostat API",
        "topic":"Population",
        "url":"https:\/\/ec.europa.eu\/eurostat\/data\/database"
    },
    {
        "title":"Self-reported unmet needs for specific health care-related services due to financial reasons by level of disability (activity limitation), sex and age",
        "start":"2022-10-27",
        "country":"EU",
        "source":"Eurostat API",
        "topic":"Population",
        "url":"https:\/\/ec.europa.eu\/eurostat\/data\/database"
    },
    {
        "title":"Immi- en emigratie; geslacht, leeftijd, nationaliteit en regio, 2010-2021",
        "start":"2022-10-07",
        "country":"Netherlands",
        "source":"CBS API",
        "topic":"Demography",
        "url":"https:\/\/opendata.cbs.nl\/statline"
    },
    {
        "title":"Immigratie en emigratie; geslacht, leeftijd, geboorteland, regio; 2010-2021",
        "start":"2022-09-19",
        "country":"Netherlands",
        "source":"CBS API",
        "topic":"Demography",
        "url":"https:\/\/opendata.cbs.nl\/statline"
    },
    {
        "title":"Lev geboren kind; huishoudenssamenstelling migratieachtergr; 2010-2021",
        "start":"2022-07-29",
        "country":"Netherlands",
        "source":"CBS API",
        "topic":"Demography",
        "url":"https:\/\/opendata.cbs.nl\/statline"
    },
    {
        "title":"Health graduates - historical data (1980-2021)",
        "start":"2022-07-12",
        "country":"EU",
        "source":"Eurostat API",
        "topic":"Population",
        "url":"https:\/\/ec.europa.eu\/eurostat\/data\/database"
    },
    {
        "title":"Self-reported unmet needs for specific health care-related services due to financial reasons by sex, age and income quintile",
        "start":"2022-03-23",
        "country":"EU",
        "source":"Eurostat API",
        "topic":"Population",
        "url":"https:\/\/ec.europa.eu\/eurostat\/data\/database"
    },
    {
        "title":"Self-reported unmet needs for specific health care-related services due to financial reasons by sex, age and educational attainment level",
        "start":"2022-02-24",
        "country":"EU",
        "source":"Eurostat API",
        "topic":"Population",
        "url":"https:\/\/ec.europa.eu\/eurostat\/data\/database"
    },
    {
        "title":"Self-reported unmet needs for health care by sex, age, specific reasons and income quintile",
        "start":"2021-11-18",
        "country":"EU",
        "source":"Eurostat API",
        "topic":"Population",
        "url":"https:\/\/ec.europa.eu\/eurostat\/data\/database"
    },
    {
        "title":"Self-reported unmet needs for health care by sex, age, specific reasons and educational attainment level",
        "start":"2021-11-16",
        "country":"EU",
        "source":"Eurostat API",
        "topic":"Population",
        "url":"https:\/\/ec.europa.eu\/eurostat\/data\/database"
    },
    {
        "title":"Average population (mid-year)",
        "start":"2020-05-28",
        "country":"EU",
        "source":"Eurostat API",
        "topic":"Population",
        "url":"https:\/\/ec.europa.eu\/eurostat\/data\/database"
    },
    {
        "title":"Population on 1 January by sex and by age group",
        "start":"2020-05-28",
        "country":"EU",
        "source":"Eurostat API",
        "topic":"Population",
        "url":"https:\/\/ec.europa.eu\/eurostat\/data\/database"
    },
    {
        "title":"Population connected to Wastewater Treatment",
        "start":"2020-05-28",
        "country":"EU",
        "source":"Eurostat API",
        "topic":"Population",
        "url":"https:\/\/ec.europa.eu\/eurostat\/data\/database"
    },
    {
        "title":"Healthy life years (1995 - 2003)",
        "start":"2011-10-05",
        "country":"EU",
        "source":"Eurostat API",
        "topic":"Population",
        "url":"https:\/\/ec.europa.eu\/eurostat\/data\/database"
    }
]